{
  "_README": "Consulting24 Crypto Licensing Index — SOURCE DATA. Fill each jurisdiction's fields from REAL, ANONYMIZED delivery records (no client names/PII). build_licensing_index.py publishes ONLY jurisdictions with sample_size>0 and cost+timeline filled; placeholders (null) are skipped. See docs/licensing-index-methodology.md.",
  "index_name": "Consulting24 Crypto Licensing Index",
  "edition": "2026",
  "total_deliveries": null,
  "methodology_url": "https://www.consulting24.co/licensing-index/methodology/",
  "disclaimer": "Aggregated, anonymized outcomes from Consulting24 client engagements. No personally identifiable client information. General guidance, not legal advice; regulations change.",
  "jurisdictions": [
    {
      "slug": "panama",
      "name": "Panama",
      "service_model": "direct",
      "sample_size": null,
      "period": "2018-2026",
      "setup_cost_eur": {
        "low": null,
        "typical": null,
        "high": null
      },
      "timeline_weeks": {
        "low": null,
        "typical": null,
        "high": null
      },
      "approval_rate_pct": null,
      "top_rejection_reasons": [],
      "notes": ""
    },
    {
      "slug": "lithuania",
      "name": "Lithuania",
      "service_model": "direct",
      "sample_size": null,
      "period": "2018-2026",
      "setup_cost_eur": {
        "low": null,
        "typical": null,
        "high": null
      },
      "timeline_weeks": {
        "low": null,
        "typical": null,
        "high": null
      },
      "approval_rate_pct": null,
      "top_rejection_reasons": [],
      "notes": ""
    },
    {
      "slug": "estonia",
      "name": "Estonia",
      "service_model": "direct",
      "sample_size": null,
      "period": "2018-2026",
      "setup_cost_eur": {
        "low": null,
        "typical": null,
        "high": null
      },
      "timeline_weeks": {
        "low": null,
        "typical": null,
        "high": null
      },
      "approval_rate_pct": null,
      "top_rejection_reasons": [],
      "notes": ""
    },
    {
      "slug": "czech-republic",
      "name": "Czech Republic",
      "service_model": "advise-and-coordinate",
      "sample_size": null,
      "period": "2018-2026",
      "setup_cost_eur": {
        "low": null,
        "typical": null,
        "high": null
      },
      "timeline_weeks": {
        "low": null,
        "typical": null,
        "high": null
      },
      "approval_rate_pct": null,
      "top_rejection_reasons": [],
      "notes": ""
    },
    {
      "slug": "poland",
      "name": "Poland",
      "service_model": "advise-and-coordinate",
      "sample_size": null,
      "period": "2018-2026",
      "setup_cost_eur": {
        "low": null,
        "typical": null,
        "high": null
      },
      "timeline_weeks": {
        "low": null,
        "typical": null,
        "high": null
      },
      "approval_rate_pct": null,
      "top_rejection_reasons": [],
      "notes": ""
    },
    {
      "slug": "malta",
      "name": "Malta",
      "service_model": "advise-and-coordinate",
      "sample_size": null,
      "period": "2018-2026",
      "setup_cost_eur": {
        "low": null,
        "typical": null,
        "high": null
      },
      "timeline_weeks": {
        "low": null,
        "typical": null,
        "high": null
      },
      "approval_rate_pct": null,
      "top_rejection_reasons": [],
      "notes": ""
    },
    {
      "slug": "cyprus",
      "name": "Cyprus",
      "service_model": "advise-and-coordinate",
      "sample_size": null,
      "period": "2018-2026",
      "setup_cost_eur": {
        "low": null,
        "typical": null,
        "high": null
      },
      "timeline_weeks": {
        "low": null,
        "typical": null,
        "high": null
      },
      "approval_rate_pct": null,
      "top_rejection_reasons": [],
      "notes": ""
    },
    {
      "slug": "switzerland",
      "name": "Switzerland",
      "service_model": "advise-and-coordinate",
      "sample_size": null,
      "period": "2018-2026",
      "setup_cost_eur": {
        "low": null,
        "typical": null,
        "high": null
      },
      "timeline_weeks": {
        "low": null,
        "typical": null,
        "high": null
      },
      "approval_rate_pct": null,
      "top_rejection_reasons": [],
      "notes": ""
    },
    {
      "slug": "cayman-islands",
      "name": "Cayman Islands",
      "service_model": "advise-and-coordinate",
      "sample_size": null,
      "period": "2018-2026",
      "setup_cost_eur": {
        "low": null,
        "typical": null,
        "high": null
      },
      "timeline_weeks": {
        "low": null,
        "typical": null,
        "high": null
      },
      "approval_rate_pct": null,
      "top_rejection_reasons": [],
      "notes": ""
    },
    {
      "slug": "bvi",
      "name": "BVI",
      "service_model": "advise-and-coordinate",
      "sample_size": null,
      "period": "2018-2026",
      "setup_cost_eur": {
        "low": null,
        "typical": null,
        "high": null
      },
      "timeline_weeks": {
        "low": null,
        "typical": null,
        "high": null
      },
      "approval_rate_pct": null,
      "top_rejection_reasons": [],
      "notes": ""
    },
    {
      "slug": "seychelles",
      "name": "Seychelles",
      "service_model": "advise-and-coordinate",
      "sample_size": null,
      "period": "2018-2026",
      "setup_cost_eur": {
        "low": null,
        "typical": null,
        "high": null
      },
      "timeline_weeks": {
        "low": null,
        "typical": null,
        "high": null
      },
      "approval_rate_pct": null,
      "top_rejection_reasons": [],
      "notes": ""
    },
    {
      "slug": "canada",
      "name": "Canada",
      "service_model": "advise-and-coordinate",
      "sample_size": null,
      "period": "2018-2026",
      "setup_cost_eur": {
        "low": null,
        "typical": null,
        "high": null
      },
      "timeline_weeks": {
        "low": null,
        "typical": null,
        "high": null
      },
      "approval_rate_pct": null,
      "top_rejection_reasons": [],
      "notes": ""
    },
    {
      "slug": "singapore",
      "name": "Singapore",
      "service_model": "advise-and-coordinate",
      "sample_size": null,
      "period": "2018-2026",
      "setup_cost_eur": {
        "low": null,
        "typical": null,
        "high": null
      },
      "timeline_weeks": {
        "low": null,
        "typical": null,
        "high": null
      },
      "approval_rate_pct": null,
      "top_rejection_reasons": [],
      "notes": ""
    },
    {
      "slug": "hong-kong",
      "name": "Hong Kong",
      "service_model": "advise-and-coordinate",
      "sample_size": null,
      "period": "2018-2026",
      "setup_cost_eur": {
        "low": null,
        "typical": null,
        "high": null
      },
      "timeline_weeks": {
        "low": null,
        "typical": null,
        "high": null
      },
      "approval_rate_pct": null,
      "top_rejection_reasons": [],
      "notes": ""
    },
    {
      "slug": "georgia",
      "name": "Georgia",
      "service_model": "advise-and-coordinate",
      "sample_size": null,
      "period": "2018-2026",
      "setup_cost_eur": {
        "low": null,
        "typical": null,
        "high": null
      },
      "timeline_weeks": {
        "low": null,
        "typical": null,
        "high": null
      },
      "approval_rate_pct": null,
      "top_rejection_reasons": [],
      "notes": ""
    },
    {
      "slug": "mauritius",
      "name": "Mauritius",
      "service_model": "advise-and-coordinate",
      "sample_size": null,
      "period": "2018-2026",
      "setup_cost_eur": {
        "low": null,
        "typical": null,
        "high": null
      },
      "timeline_weeks": {
        "low": null,
        "typical": null,
        "high": null
      },
      "approval_rate_pct": null,
      "top_rejection_reasons": [],
      "notes": ""
    },
    {
      "slug": "gibraltar",
      "name": "Gibraltar",
      "service_model": "advise-and-coordinate",
      "sample_size": null,
      "period": "2018-2026",
      "setup_cost_eur": {
        "low": null,
        "typical": null,
        "high": null
      },
      "timeline_weeks": {
        "low": null,
        "typical": null,
        "high": null
      },
      "approval_rate_pct": null,
      "top_rejection_reasons": [],
      "notes": ""
    },
    {
      "slug": "bahamas",
      "name": "Bahamas",
      "service_model": "advise-and-coordinate",
      "sample_size": null,
      "period": "2018-2026",
      "setup_cost_eur": {
        "low": null,
        "typical": null,
        "high": null
      },
      "timeline_weeks": {
        "low": null,
        "typical": null,
        "high": null
      },
      "approval_rate_pct": null,
      "top_rejection_reasons": [],
      "notes": ""
    },
    {
      "slug": "costa-rica",
      "name": "Costa Rica",
      "service_model": "advise-and-coordinate",
      "sample_size": null,
      "period": "2018-2026",
      "setup_cost_eur": {
        "low": null,
        "typical": null,
        "high": null
      },
      "timeline_weeks": {
        "low": null,
        "typical": null,
        "high": null
      },
      "approval_rate_pct": null,
      "top_rejection_reasons": [],
      "notes": ""
    },
    {
      "slug": "el-salvador",
      "name": "El Salvador",
      "service_model": "advise-and-coordinate",
      "sample_size": null,
      "period": "2018-2026",
      "setup_cost_eur": {
        "low": null,
        "typical": null,
        "high": null
      },
      "timeline_weeks": {
        "low": null,
        "typical": null,
        "high": null
      },
      "approval_rate_pct": null,
      "top_rejection_reasons": [],
      "notes": ""
    },
    {
      "slug": "dubai",
      "name": "Dubai",
      "service_model": "comparison-only",
      "sample_size": null,
      "period": "2018-2026",
      "setup_cost_eur": {
        "low": null,
        "typical": null,
        "high": null
      },
      "timeline_weeks": {
        "low": null,
        "typical": null,
        "high": null
      },
      "approval_rate_pct": null,
      "top_rejection_reasons": [],
      "notes": ""
    },
    {
      "slug": "abu-dhabi",
      "name": "Abu Dhabi",
      "service_model": "comparison-only",
      "sample_size": null,
      "period": "2018-2026",
      "setup_cost_eur": {
        "low": null,
        "typical": null,
        "high": null
      },
      "timeline_weeks": {
        "low": null,
        "typical": null,
        "high": null
      },
      "approval_rate_pct": null,
      "top_rejection_reasons": [],
      "notes": ""
    }
  ]
}